odoo9_addon_base_country_state_translatable-9.0.1.0.0-py2.7-nspkg.pth
odoo9_addon_base_country_state_translatable-9.0.1.0.0.dist-info/DESCRIPTION.rst
odoo9_addon_base_country_state_translatable-9.0.1.0.0.dist-info/METADATA
odoo9_addon_base_country_state_translatable-9.0.1.0.0.dist-info/RECORD
odoo9_addon_base_country_state_translatable-9.0.1.0.0.dist-info/WHEEL
odoo9_addon_base_country_state_translatable-9.0.1.0.0.dist-info/metadata.json
odoo9_addon_base_country_state_translatable-9.0.1.0.0.dist-info/namespace_packages.txt
odoo9_addon_base_country_state_translatable-9.0.1.0.0.dist-info/top_level.txt
odoo_addons/base_country_state_translatable/README.rst
odoo_addons/base_country_state_translatable/__init__.py
odoo_addons/base_country_state_translatable/__openerp__.py
odoo_addons/base_country_state_translatable/models/__init__.py
odoo_addons/base_country_state_translatable/models/res_country.py
